opendsa/__init__.py
opendsa-0.0.0.dist-info/METADATA
opendsa-0.0.0.dist-info/WHEEL
opendsa-0.0.0.dist-info/top_level.txt
opendsa-0.0.0.dist-info/RECORD
