Metadata-Version: 2.1
Name: opendsa
Version: 0.0.0
Summary: Coming soon
Author-email: Hayden How <hayden@haydenhow.com>
